photorepl/__init__.py
photorepl/__main__.py
photorepl/photo.py
photorepl/threads.py
photoREPL-0.0.3.dist-info/DESCRIPTION.rst
photoREPL-0.0.3.dist-info/WHEEL
photoREPL-0.0.3.dist-info/RECORD
photoREPL-0.0.3.dist-info/metadata.json
photoREPL-0.0.3.dist-info/METADATA
photoREPL-0.0.3.dist-info/top_level.txt
